{
  "movies" : {
    "0" : {
      "director" : "Martin Scorsese",
      "title" : "Goodfellas",
      "year" : 1990
    },
    "1" : {
      "director" : "George Lucas",
      "title" : "Star Wars",
      "year" : 1977
    },
    "2" : {
      "director" : "Ridley Scott",
      "title" : "Blade Runner",
      "year" : 1982
    },
    "-MCKUOh1Yt2Wr3cgUQyU" : {
      "director" : "Quentin Tarantino",
      "title" : "Pulp Fiction",
      "year" : "1994"
    },
    "-MCKUQ0w5iiimhDz0Gz7" : {
      "director" : "Quentin Tarantino",
      "title" : "Pulp Fiction",
      "year" : "1994"
    }
  }
}
